status_cog/__init__.py
status_cog/cog.py
status_cog-0.1.0a2.dist-info/LICENSE
status_cog-0.1.0a2.dist-info/WHEEL
status_cog-0.1.0a2.dist-info/METADATA
status_cog-0.1.0a2.dist-info/RECORD
